wxdata/__init__.py
wxdata/aigefs/__init__.py
wxdata/aigefs/aigefs.py
wxdata/aigefs/paths.py
wxdata/aigefs/url_scanners.py
wxdata/aigfs/__init__.py
wxdata/aigfs/aigfs.py
wxdata/aigfs/paths.py
wxdata/aigfs/url_scanners.py
wxdata/calc/__init__.py
wxdata/calc/derived_fields.py
wxdata/calc/kinematics.py
wxdata/calc/thermodynamics.py
wxdata/calc/unit_conversion.py
wxdata/client/__init__.py
wxdata/client/client.py
wxdata/ecmwf/__init__.py
wxdata/ecmwf/ecmwf.py
wxdata/ecmwf/file_funcs.py
wxdata/ecmwf/paths.py
wxdata/ecmwf/url_scanners.py
wxdata/fems/__init__.py
wxdata/fems/fems.py
wxdata/fems/raws_sigs.py
wxdata/gefs/__init__.py
wxdata/gefs/exception_messages.py
wxdata/gefs/file_funcs.py
wxdata/gefs/gefs.py
wxdata/gefs/paths.py
wxdata/gefs/process.py
wxdata/gefs/url_scanners.py
wxdata/gfs/__init__.py
wxdata/gfs/exception_messages.py
wxdata/gfs/gfs.py
wxdata/gfs/paths.py
wxdata/gfs/url_scanners.py
wxdata/metars/__init__.py
wxdata/metars/_clean_data.py
wxdata/metars/metar_obs.py
wxdata/noaa/__init__.py
wxdata/noaa/nws.py
wxdata/post_processors/__init__.py
wxdata/post_processors/aigefs_post_processing.py
wxdata/post_processors/aigfs_post_processing.py
wxdata/post_processors/ecmwf_post_processing.py
wxdata/post_processors/gefs_post_processing.py
wxdata/post_processors/gfs_post_processing.py
wxdata/post_processors/rtma_post_processing.py
wxdata/rtma/__init__.py
wxdata/rtma/file_funcs.py
wxdata/rtma/keys.py
wxdata/rtma/process.py
wxdata/rtma/rtma.py
wxdata/rtma/url_scanners.py
wxdata/soundings/__init__.py
wxdata/soundings/_exceptions.py
wxdata/soundings/wyoming_soundings.py
wxdata/utils/__init__.py
wxdata/utils/coords.py
wxdata/utils/file_funcs.py
wxdata/utils/file_scanner.py
wxdata/utils/nomads_gribfilter.py
wxdata/utils/recycle_bin.py
wxdata/utils/scripts.py
wxdata/utils/tools.py
wxdata/utils/xmacis2_cleanup.py
wxdata-1.2.7.dist-info/licenses/LICENSE
wxdata-1.2.7.dist-info/METADATA
wxdata-1.2.7.dist-info/WHEEL
wxdata-1.2.7.dist-info/top_level.txt
wxdata-1.2.7.dist-info/RECORD
