Metadata-Version: 2.4
Name: wxdata
Version: 1.2.7
Summary: A Python library that acts as a client to download, pre-process and post-process weather data. Friendly for users on VPN/PROXY connections.
Author: Eric J. Drewitz
Project-URL: Documentation, https://github.com/edrewitz/wxdata/blob/main/Documentation/Landing%20Page.md
Project-URL: Repository, https://github.com/edrewitz/wxdata/tree/main
Keywords: meteorology,atmospheric sciences
Classifier: Programming Language :: Python
Classifier: Topic :: Scientific/Engineering
Classifier: Topic :: Scientific/Engineering :: Atmospheric Science
Classifier: Operating System :: OS Independent
Requires-Python: >=3.10
License-File: LICENSE
Requires-Dist: metpy>=1.5.1
Requires-Dist: numpy>=1.24
Requires-Dist: pandas>=2.2
Requires-Dist: xarray>=2023.1.0
Requires-Dist: netcdf4>=1.7.1
Requires-Dist: cartopy>=0.21.0
Requires-Dist: beautifulsoup4>=4.13.4
Requires-Dist: requests>=2.32.4
Requires-Dist: cfgrib>=0.9.10.4
Requires-Dist: dask>=2025.5.1
Dynamic: license-file
